README.md
setup.py
roc/__init__.py
roc/channel.py
roc/channel_manager.py
roc/data_formatter.py
roc/id_generator.py
roc/packer.py
roc/packet.py
roc/request.py
roc/socket.py
roc_py.egg-info/PKG-INFO
roc_py.egg-info/SOURCES.txt
roc_py.egg-info/dependency_links.txt
roc_py.egg-info/top_level.txt
tests/__init__.py
tests/main.py