Metadata-Version: 2.1
Name: roc-py
Version: 0.2.2
Summary: Hyperf 多路复用 RPC 组件 Python 版本
Home-page: https://github.com/hyperf/roc-py
Author: limingxinleo
Author-email: l@hyperf.io
Classifier: Programming Language :: Python :: 3
Classifier: License :: OSI Approved :: MIT License
Classifier: Operating System :: OS Independent
